erpnext_ko/__init__.py
erpnext_ko/hooks.py
erpnext_ko/install.py
erpnext_ko/config/__init__.py
erpnext_ko/config/desktop.py
erpnext_ko/locales/__init__.py
erpnext_ko/locales/ko.csv
erpnext_ko-0.1.2.dist-info/METADATA
erpnext_ko-0.1.2.dist-info/WHEEL
erpnext_ko-0.1.2.dist-info/top_level.txt
erpnext_ko-0.1.2.dist-info/RECORD
