Metadata-Version: 2.4
Name: erpnext-ko
Version: 0.1.2
Summary: Korean localisation pack for ERPNext deployments.
Author: ERPNext MCP
License: MIT
Classifier: Programming Language :: Python :: 3
Classifier: License :: OSI Approved :: MIT License
Classifier: Operating System :: OS Independent
Requires-Python: >=3.10
Provides-Extra: dev
Requires-Dist: black; extra == "dev"
Requires-Dist: isort; extra == "dev"
